scw_py_client/__init__.py
scw_py_client/client_api.py
scw_py_client/core.py
scw_py_client/models/__init__.py
scw_py_client/models/functions.py
scw_py_client/models/k8s.py
scw_py_client/models/pagination.py
scw_py_client/models/rdb.py
scw_py_client/models/region.py
scw_py_client/models/registry.py
scw_py_client-0.1.2.dist-info/LICENSE
scw_py_client-0.1.2.dist-info/METADATA
scw_py_client-0.1.2.dist-info/WHEEL
scw_py_client-0.1.2.dist-info/top_level.txt
scw_py_client-0.1.2.dist-info/RECORD
