Metadata-Version: 2.1
Name: scw-py-client
Version: 0.1.2
Summary: scaleway python client to interact with the scaleway API
Home-page: https://github.com/italents/scw-py-client
Author: italents
Author-email: author@example.com
License: UNKNOWN
Project-URL: Bug Tracker, https://github.com/italents/scw-py-client/issues
Platform: UNKNOWN
Classifier: Programming Language :: Python :: 3
Classifier: License :: OSI Approved :: MIT License
Classifier: Operating System :: OS Independent
Requires-Python: >=3.6
License-File: LICENSE
Requires-Dist: pydantic
Requires-Dist: requests
Requires-Dist: boto3
